spec_dev/__init__.py
spec_dev/cli.py
spec_dev/data/__init__.py
spec_dev/data/.spec-dev/AGENTS.md
spec_dev/data/.spec-dev/architect.md
spec_dev/data/.spec-dev/coder.md
spec_dev/data/.spec-dev/tasker.md
spec_dev-0.5.6.dist-info/METADATA
spec_dev-0.5.6.dist-info/WHEEL
spec_dev-0.5.6.dist-info/entry_points.txt
spec_dev-0.5.6.dist-info/top_level.txt
spec_dev-0.5.6.dist-info/RECORD
