Metadata-Version: 2.4
Name: spec-dev
Version: 0.5.6
Summary: Bundle of the .spec-dev workspace template.
Author: Spec Dev
Project-URL: Homepage, https://example.com/spec-dev
Classifier: Programming Language :: Python
Classifier: Programming Language :: Python :: 3
Classifier: Programming Language :: Python :: 3 :: Only
Classifier: Programming Language :: Python :: 3.9
Classifier: Programming Language :: Python :: 3.10
Classifier: Programming Language :: Python :: 3.11
Classifier: Programming Language :: Python :: 3.12
Requires-Python: >=3.9
